cps3utils/__init__.py
cps3utils/__main__.py
cps3utils/convert.py
cps3utils/crypt.py
cps3utils/load.py
cps3utils/games/__init__.py
cps3utils/games/jojoban.py
cps3utils-0.1.3.dist-info/METADATA
cps3utils-0.1.3.dist-info/WHEEL
cps3utils-0.1.3.dist-info/top_level.txt
cps3utils-0.1.3.dist-info/RECORD
